xlsx_to_html_extractor/__init__.py
xlsx_to_html_extractor/xlsx_extractor.py
xlsx_to_html_extractor-0.1.0.dist-info/LICENSE
xlsx_to_html_extractor-0.1.0.dist-info/METADATA
xlsx_to_html_extractor-0.1.0.dist-info/WHEEL
xlsx_to_html_extractor-0.1.0.dist-info/top_level.txt
xlsx_to_html_extractor-0.1.0.dist-info/RECORD
